{
    "sec_cik": "0000003153",
    "sec_company_name": "ALABAMA POWER CO (Filer)",
    "document_type": "10K",
    "sec_form_header": "Form 10-K",
    "sec_period_of_report": "20181231",
    "sec_filing_date": "20190220",
    "sec_changed_date": "20190219",
    "sec_accepted_date": "20190219183401",
    "sec_index_url": "https://www.sec.gov//Archives/edgar/data/92122/000009212219000006/0000092122-19-000006-index.htm",
    "sec_url": "https://www.sec.gov//Archives/edgar/data/92122/000009212219000006/0000092122-19-000006.txt",
    "metadata_file_name": "/home/koshy/Desktop/Capstone/fintech/data/SEC/batch_0001/003/SO_0000003153_10K_20181231_Item1A_metadata.json",
    "original_file_name": "",
    "original_file_size": "18438149 chars",
    "document_group": "10-K",
    "section_name": "Item1A",
    "section_n_characters": 107507,
    "endpoints": [
        "Item 1A. RISK FACTORS",
        "Item 2. PROPERTIES"
    ],
    "extraction_method": "html",
    "warnings": [],
    "company_description": "SO",
    "output_file": "/home/koshy/Desktop/Capstone/fintech/data/SEC/batch_0001/003/SO_0000003153_10K_20181231_Item1A_excerpt.txt",
    "time_elapsed": 7.5,
    "batch_number": 1,
    "batch_signature": "",
    "batch_start_time": "2020-01-15 02:06:11.586534",
    "batch_machine_id": "koshy-Legion",
    "section_end_time": "2020-01-15 02:32:35.526603"
}